LICENSE
README.md
setup.py
lmft/__init__.py
lmft/chatglm_model.py
lmft/chatglm_utils.py
lmft/gpt2-sentiment.py
lmft/gpt2-sentiment_peft.py
lmft/gpt2_sentiment.py
lmft/gpt_neox_sentiment_trl_peft.py
lmft/lmft.py
lmft/t5-sentiment.py
lmft/version.py
lmft.egg-info/PKG-INFO
lmft.egg-info/SOURCES.txt
lmft.egg-info/dependency_links.txt
lmft.egg-info/not-zip-safe
lmft.egg-info/requires.txt
lmft.egg-info/top_level.txt