Metadata-Version: 2.1
Name: lmft
Version: 0.2.5
Summary: Language Model Fine-tuning Toolkit (LMFT)
Home-page: https://github.com/shibing624/lmft
Author: XuMing
Author-email: xuming624@qq.com
License: Apache License 2.0
Keywords: lmft,GPT2,transformers,pytorch,language model
Platform: UNKNOWN
Classifier: Development Status :: 5 - Production/Stable
Classifier: Intended Audience :: Developers
Classifier: Intended Audience :: Education
Classifier: Intended Audience :: Science/Research
Classifier: License :: OSI Approved :: Apache Software License
Classifier: Operating System :: OS Independent
Classifier: Programming Language :: Python :: 3
Classifier: Topic :: Scientific/Engineering :: Artificial Intelligence
Requires-Python: >=3.7.0
Provides-Extra: dev
Provides-Extra: test
